LICENSE
MANIFEST.in
README.rst
setup.cfg
setup.py
versioneer.py
artellapipe/__init__.py
artellapipe/tools/__init__.py
artellapipe/tools/playblastmanager/__init__.py
artellapipe/tools/playblastmanager/__logging__.ini
artellapipe/tools/playblastmanager/__version__.py
artellapipe/tools/playblastmanager/_version.py
artellapipe/tools/playblastmanager/core/__init__.py
artellapipe/tools/playblastmanager/core/defines.py
artellapipe/tools/playblastmanager/core/playblastmanager.py
artellapipe/tools/playblastmanager/core/plugin.py
artellapipe/tools/playblastmanager/plugins/__init__.py
artellapipe/tools/playblastmanager/plugins/cameras.py
artellapipe/tools/playblastmanager/plugins/codec.py
artellapipe/tools/playblastmanager/plugins/displayoptions.py
artellapipe/tools/playblastmanager/plugins/options.py
artellapipe/tools/playblastmanager/plugins/panzoom.py
artellapipe/tools/playblastmanager/plugins/renderer.py
artellapipe/tools/playblastmanager/plugins/resolution.py
artellapipe/tools/playblastmanager/plugins/save.py
artellapipe/tools/playblastmanager/plugins/stamp.py
artellapipe/tools/playblastmanager/plugins/timerange.py
artellapipe/tools/playblastmanager/plugins/tracking.py
artellapipe/tools/playblastmanager/plugins/viewport.py
artellapipe/tools/playblastmanager/resources/images/no_plugins_available.png
artellapipe/tools/playblastmanager/resources/images/playblastmanager_logo.png
artellapipe/tools/playblastmanager/widgets/__init__.py
artellapipe/tools/playblastmanager/widgets/playblastmanager.py
artellapipe/tools/playblastmanager/widgets/presets.py
artellapipe/tools/playblastmanager/widgets/preview.py
artellapipe_tools_playblastmanager.egg-info/PKG-INFO
artellapipe_tools_playblastmanager.egg-info/SOURCES.txt
artellapipe_tools_playblastmanager.egg-info/dependency_links.txt
artellapipe_tools_playblastmanager.egg-info/not-zip-safe
artellapipe_tools_playblastmanager.egg-info/requires.txt
artellapipe_tools_playblastmanager.egg-info/top_level.txt
tests/__init__.py
tests/test_general.py