Metadata-Version: 2.1
Name: artellapipe-tools-playblastmanager
Version: 0.0.7
Summary: Tool to generate cutomized playblasts
Home-page: https://github.com/ArtellaPipe/artellapipe-tools-playblastmanager
Author: Tomas Poveda
Author-email: tpovedatd@gmail.com
License: MIT
Platform: UNKNOWN
Provides-Extra: dev
Provides-Extra: test
